{"skeleton":{"hash":"690w6OeqIgg","spine":"4.1.23","x":-304.66,"y":-39.48,"width":994.16,"height":1316.01,"images":"./images/","audio":"C:/Users/Alexander/Documents/gamegem/pixie"},"bones":[{"name":"root"},{"name":"torso","parent":"root","length":226.93,"rotation":128.85,"x":36.59,"y":309.39},{"name":"head","parent":"torso","length":243.21,"rotation":-30.34,"x":235.35,"y":-2.58},{"name":"arm_front","parent":"torso","length":72.93,"rotation":-125.64,"x":211.9,"y":-22.57},{"name":"arm_front2","parent":"arm_front","length":106.88,"rotation":-36.66,"x":72.93},{"name":"arm_back","parent":"torso","length":93.09,"rotation":128.45,"x":235.72,"y":69.61},{"name":"arm_back2","parent":"arm_back","length":103.94,"rotation":-52.15,"x":93.09},{"name":"legs","parent":"torso","length":79.58,"rotation":156.04,"x":21.34,"y":115.18},{"name":"legs2","parent":"legs","length":45.12,"rotation":70.95,"x":79.58},{"name":"legs1","parent":"torso","length":71.47,"rotation":157.09,"x":-46.83,"y":56.63},{"name":"legs3","parent":"legs1","length":36.01,"rotation":75.36,"x":71.47},{"name":"wing_front","parent":"torso","length":517.81,"rotation":-62.22,"x":128.2,"y":-55.5},{"name":"wing_back","parent":"torso","length":469.65,"rotation":-54.41,"x":194.56,"y":-1.8},{"name":"target","parent":"root","x":83.22,"y":433.75,"color":"ff3f00ff"},{"name":"wand_head","parent":"arm_front2","length":294.22,"rotation":-100.57,"x":80.78,"y":5.63},{"name":"confused","parent":"root","x":-136.62,"y":904.93},{"name":"confuse","parent":"confused","x":660.17,"y":74.62},{"name":"star","parent":"confused","x":804.85,"y":73.19,"scaleX":0.4,"scaleY":0.4},{"name":"confuse2","parent":"confused","x":660.17,"y":182.06},{"name":"confuse3","parent":"confused","x":660.17,"y":300.96},{"name":"star2","parent":"confused","x":804.85,"y":162,"scaleX":0.4,"scaleY":0.4},{"name":"star3","parent":"confused","x":804.85,"y":256.55,"scaleX":0.4,"scaleY":0.4},{"name":"star4","parent":"confused","x":804.85,"y":352.53,"scaleX":0.4,"scaleY":0.4}],"slots":[{"name":"shadow","bone":"root","color":"ffffff75","attachment":"shadow"},{"name":"legs","bone":"legs","attachment":"legs"},{"name":"legs1","bone":"legs1","attachment":"legs1"},{"name":"wing_back","bone":"wing_back","attachment":"wing_back"},{"name":"wing_front","bone":"wing_front","attachment":"wing_front"},{"name":"arm_back","bone":"arm_back","attachment":"arm_back"},{"name":"torso","bone":"torso","attachment":"torso"},{"name":"head","bone":"head","attachment":"head"},{"name":"mouse_defolt","bone":"head","attachment":"mouse_defolt"},{"name":"mouse_2","bone":"head","color":"ffffff00","attachment":"mouse_2"},{"name":"mouse_3","bone":"head","color":"ffffff00","attachment":"mouse_3"},{"name":"eyes","bone":"head","attachment":"eyes"},{"name":"brows","bone":"head","attachment":"brows"},{"name":"wand_head","bone":"wand_head","attachment":"wand_head"},{"name":"arm_front","bone":"arm_front","attachment":"arm_front"},{"name":"star","bone":"star","color":"ffffff00","attachment":"star"},{"name":"star2","bone":"star2","color":"ffffff00","attachment":"star"},{"name":"star3","bone":"star3","color":"ffffff00","attachment":"star"},{"name":"star4","bone":"star4","color":"ffffff00","attachment":"star"},{"name":"confuse","bone":"confuse","color":"ffffff00","attachment":"confuse"},{"name":"confuse2","bone":"confuse2","color":"ffffff00","attachment":"confuse"},{"name":"confuse3","bone":"confuse3","color":"ffffff00","attachment":"confuse"}],"ik":[{"name":"target","bones":["arm_front","arm_front2"],"target":"target","bendPositive":false}],"skins":[{"name":"default","attachments":{"arm_back":{"arm_back":{"type":"mesh","uvs":[0.82711,0,0.90997,0.02695,1,0.1155,1,0.18254,0.95921,0.41787,0.86999,0.54535,0.84459,0.58165,0.81645,0.62187,0.7379,0.7341,0.36731,0.97213,0.25797,1,0.2192,1,0.14194,0.93247,0,0.66342,0,0.62501,0.0658,0.53716,0.35778,0.53674,0.43507,0.47854,0.50575,0.39872,0.53008,0.37125,0.5528,0.34067,0.60221,0.27421,0.69834,0.03607,0.81176,0],"triangles":[9,10,12,10,11,12,12,16,9,8,16,17,8,9,16,12,13,16,16,13,15,8,17,7,7,17,18,13,14,15,18,19,7,7,19,6,6,19,20,6,20,21,23,6,21,5,6,23,22,23,21,4,5,23,3,4,0,0,4,23,3,0,1,1,2,3],"vertices":[1,5,-7.83,-2.64,1,1,5,-6.26,11.81,1,1,5,5.58,29.79,1,1,5,17.02,32.37,1,1,5,58.69,34.81,1,2,5,83.71,25.27,0.98601,6,-25.71,8.09,0.01399,2,5,90.83,22.55,0.90185,6,-19.19,12.05,0.09815,2,5,98.72,19.54,0.64935,6,-11.97,16.44,0.35065,2,5,120.75,11.14,0.02654,6,8.18,28.67,0.97346,1,6,81.57,40.23,1,1,6,100.07,36.93,1,1,6,105.89,34.19,1,1,6,112.48,18.05,1,1,6,113.79,-34.59,1,1,6,110.94,-40.67,1,1,6,94.52,-49.94,1,2,5,100.92,-58.01,0.02392,6,50.61,-29.41,0.97608,2,5,88.16,-47.73,0.16771,6,34.67,-33.18,0.83229,2,5,71.96,-39.36,0.51374,6,18.11,-40.83,0.48626,2,5,66.38,-36.47,0.64805,6,12.41,-43.47,0.35195,2,5,60.33,-33.97,0.77072,6,6.72,-46.71,0.22928,2,5,47.18,-28.52,0.93862,6,-5.64,-53.75,0.06138,1,5,3.02,-22.11,1,1,5,-7.27,-5.13,1],"hull":24,"edges":[0,46,0,2,2,4,4,6,6,8,16,18,18,20,20,22,22,24,24,26,26,28,28,30,30,32,32,34,42,44,44,46,14,16,12,14,8,10,10,12,38,40,40,42,34,36,36,38],"width":166,"height":175}},"arm_front":{"arm_front":{"type":"mesh","uvs":[0.57501,0.06291,0.72943,0.1816,0.95865,0.41825,1,0.55006,1,0.63953,0.81132,0.97383,0.78977,0.9849,0.67514,0.9848,0.59925,0.63821,0.53119,0.57573,0.47185,0.54449,0.43196,0.52348,0.38651,0.49956,0.28049,0.46586,0.10477,0.47498,0.03249,0.41769,0,0.26723,0,0.25317,0.05713,0.07345,0.24624,0,0.27081,0,0.481,0.02407,0.5321,0.02993],"triangles":[5,6,8,6,7,8,5,8,4,8,2,4,2,3,4,8,1,2,8,9,1,1,9,0,9,10,0,22,0,21,21,0,11,11,0,10,11,12,21,12,13,21,14,19,13,19,20,13,18,14,17,14,18,19,13,20,21,14,15,16,14,16,17],"vertices":[2,3,102.92,18.97,0.05424,4,12.73,33.12,0.94576,1,4,47.2,37.26,1,1,4,102.73,36.78,1,1,4,119.18,26.96,1,1,4,125.64,17.18,1,1,4,118.13,-40.27,1,1,4,115.32,-43.87,1,1,4,96.09,-56.55,1,2,3,103.56,-56.55,4.7E-4,4,58.33,-27.08,0.99953,2,3,90.36,-47.61,0.02832,4,42.41,-27.79,0.97168,2,3,78.68,-42.86,0.12946,4,30.2,-30.95,0.87054,2,3,70.83,-39.66,0.26138,4,21.99,-33.07,0.73862,2,3,61.88,-36.02,0.47626,4,12.64,-35.49,0.52374,2,3,40.85,-30.41,0.89511,4,-7.57,-43.55,0.10489,1,3,5.52,-29.63,1,1,3,-8.56,-21.32,1,1,3,-13.98,-1.27,1,1,3,-13.87,0.57,1,1,3,-1.09,23.43,1,1,3,37.4,30.9,1,1,3,42.33,30.63,1,2,3,84.34,25.11,0.37649,4,-5.84,26.95,0.62351,2,3,94.55,23.77,0.16027,4,3.15,31.97,0.83973],"hull":23,"edges":[2,4,4,6,6,8,8,10,10,12,12,14,14,16,16,18,24,26,26,28,28,30,30,32,32,34,34,36,36,38,38,40,40,42,42,44,2,0,0,44,22,24,18,20,20,22],"width":201,"height":131}},"brows":{"brows":{"x":103.73,"y":80.14,"rotation":-98.51,"width":134,"height":43}},"confuse":{"confuse":{"x":-4.54,"y":-7.28,"width":223,"height":101}},"confuse2":{"confuse":{"x":-4.54,"y":-7.28,"width":223,"height":101}},"confuse3":{"confuse":{"x":-4.54,"y":-7.28,"width":223,"height":101}},"eyes":{"eyes":{"x":73.59,"y":78.08,"rotation":-98.51,"width":119,"height":38}},"head":{"head":{"x":139.57,"y":35.85,"rotation":-98.51,"width":279,"height":395}},"legs":{"legs":{"x":57.03,"y":13.13,"rotation":75.11,"width":97,"height":135}},"legs1":{"legs1":{"x":52.14,"y":10.05,"rotation":74.05,"width":97,"height":135}},"mouse_2":{"mouse_2":{"x":14.41,"y":77.84,"rotation":-98.51,"width":33,"height":35}},"mouse_3":{"mouse_3":{"x":25.81,"y":69.56,"rotation":-98.51,"width":116,"height":52}},"mouse_defolt":{"mouse_defolt":{"x":16.71,"y":72.94,"rotation":-98.51,"width":114,"height":33}},"shadow":{"shadow":{"x":1.34,"y":15.52,"width":462,"height":110}},"star":{"star":{"x":3.16,"y":-2.31,"width":100,"height":100}},"star2":{"star":{"x":3.16,"y":-2.31,"width":100,"height":100}},"star3":{"star":{"x":3.16,"y":-2.31,"width":100,"height":100}},"star4":{"star":{"x":3.16,"y":-2.31,"width":100,"height":100}},"torso":{"torso":{"x":88.17,"y":45.49,"rotation":-128.85,"width":321,"height":324}},"wand_head":{"wand_head":{"x":136.93,"y":-16.06,"rotation":134.02,"width":331,"height":338}},"wing_back":{"wing_back":{"x":174.69,"y":-29.11,"rotation":-74.44,"width":257,"height":660}},"wing_front":{"wing_front":{"x":207.26,"y":-29.7,"rotation":-66.63,"width":359,"height":660}}}}],"animations":{"attack":{"slots":{"mouse_2":{"rgba":[{"time":0.3667,"color":"ffffff00"},{"time":0.4,"color":"ffffffff"}]},"mouse_3":{"rgba":[{"color":"ffffffff","curve":"stepped"},{"time":0.3667,"color":"ffffffff"},{"time":0.4,"color":"ffffff00"}]},"mouse_defolt":{"rgba":[{"color":"ffffff00"}]}},"bones":{"torso":{"rotate":[{},{"time":0.3333,"value":-8.85},{"time":0.5,"value":3.29},{"time":0.6667}],"translate":[{"curve":[0.056,0,0.194,31.39,0.056,0,0.194,44.14]},{"time":0.3333,"x":31.39,"y":44.14,"curve":[0.391,31.39,0.449,2.42,0.391,44.14,0.449,-9.04]},{"time":0.5,"x":-3.94,"y":-17.98,"curve":[0.573,-12.84,0.634,0,0.573,-30.5,0.634,0]},{"time":0.6667}]},"wing_front":{"shear":[{"curve":[0.037,0,0.063,-34.87,0.037,0,0.063,14.73]},{"time":0.1,"x":-34.87,"y":14.73,"curve":[0.137,-34.87,0.198,0,0.137,14.73,0.198,0]},{"time":0.2333,"curve":[0.27,0,0.296,-34.87,0.27,0,0.296,14.73]},{"time":0.3333,"x":-34.87,"y":14.73,"curve":[0.37,-34.87,0.398,0,0.37,14.73,0.398,0]},{"time":0.4333,"curve":[0.47,0,0.496,-34.87,0.47,0,0.496,14.73]},{"time":0.5333,"x":-34.87,"y":14.73,"curve":[0.57,-34.87,0.63,0,0.57,14.73,0.63,0]},{"time":0.6667}]},"wing_back":{"shear":[{"curve":[0.037,0,0.063,48.25,0.037,0,0.063,0]},{"time":0.1,"x":48.25,"curve":[0.137,48.25,0.198,0,0.137,0,0.198,0]},{"time":0.2333,"curve":[0.27,0,0.296,48.25,0.27,0,0.296,0]},{"time":0.3333,"x":48.25,"curve":[0.37,48.25,0.398,0,0.37,0,0.398,0]},{"time":0.4333,"curve":[0.47,0,0.496,48.25,0.47,0,0.496,0]},{"time":0.5333,"x":48.25,"curve":[0.57,48.25,0.63,0,0.57,0,0.63,0]},{"time":0.6667}]},"target":{"translate":[{"x":-3.27,"y":-10.35},{"time":0.0667,"x":-182.53,"y":-85.2},{"time":0.1333,"x":-278.06,"y":26.02},{"time":0.2667,"x":-227.33,"y":196.49},{"time":0.3667,"x":-121.45,"y":264.65},{"time":0.5333,"x":-348.27,"y":-43.68},{"time":0.6,"x":-212.49,"y":-96.59},{"time":0.6667,"x":-3.27,"y":-10.35}]},"arm_back":{"rotate":[{"value":3.91,"curve":[0.034,1.67,0.067,0]},{"time":0.1,"curve":[0.211,0,0.322,18.1]},{"time":0.4333,"value":18.1,"curve":[0.511,18.1,0.59,9.22]},{"time":0.6667,"value":3.91}]},"head":{"rotate":[{"value":0.72,"curve":[0.023,0.29,0.045,0]},{"time":0.0667,"curve":[0.178,0,0.289,6.88]},{"time":0.4,"value":6.88,"curve":[0.489,6.88,0.579,2.46]},{"time":0.6667,"value":0.72}]},"legs":{"rotate":[{"value":-2.44,"curve":[0.045,-1.12,0.089,0]},{"time":0.1333,"curve":[0.244,0,0.356,-6.92]},{"time":0.4667,"value":-6.92,"curve":[0.534,-6.92,0.601,-4.44]},{"time":0.6667,"value":-2.44}]},"legs1":{"rotate":[{"value":-2.44,"curve":[0.045,-1.12,0.089,0]},{"time":0.1333,"curve":[0.244,0,0.356,-6.92]},{"time":0.4667,"value":-6.92,"curve":[0.534,-6.92,0.601,-4.44]},{"time":0.6667,"value":-2.44}]},"wand_head":{"rotate":[{"time":0.3667,"curve":[0.411,23.08,0.456,69.24]},{"time":0.5,"value":69.24,"curve":[0.556,69.24,0.611,0]},{"time":0.6667}]}}},"idle":{"bones":{"torso":{"translate":[{"curve":[0.111,0,0.222,0,0.111,0,0.222,-42.57]},{"time":0.3333,"y":-42.57,"curve":[0.444,0,0.556,0,0.444,-42.57,0.556,0]},{"time":0.6667}]},"wing_front":{"shear":[{"curve":[0.037,0,0.063,-34.87,0.037,0,0.063,14.73]},{"time":0.1,"x":-34.87,"y":14.73,"curve":[0.137,-34.87,0.198,0,0.137,14.73,0.198,0]},{"time":0.2333,"curve":[0.27,0,0.296,-34.87,0.27,0,0.296,14.73]},{"time":0.3333,"x":-34.87,"y":14.73,"curve":[0.37,-34.87,0.398,0,0.37,14.73,0.398,0]},{"time":0.4333,"curve":[0.47,0,0.496,-34.87,0.47,0,0.496,14.73]},{"time":0.5333,"x":-34.87,"y":14.73,"curve":[0.57,-34.87,0.63,0,0.57,14.73,0.63,0]},{"time":0.6667}]},"wing_back":{"shear":[{"curve":[0.037,0,0.063,48.25,0.037,0,0.063,0]},{"time":0.1,"x":48.25,"curve":[0.137,48.25,0.198,0,0.137,0,0.198,0]},{"time":0.2333,"curve":[0.27,0,0.296,48.25,0.27,0,0.296,0]},{"time":0.3333,"x":48.25,"curve":[0.37,48.25,0.398,0,0.37,0,0.398,0]},{"time":0.4333,"curve":[0.47,0,0.496,48.25,0.47,0,0.496,0]},{"time":0.5333,"x":48.25,"curve":[0.57,48.25,0.63,0,0.57,0,0.63,0]},{"time":0.6667}]},"target":{"translate":[{"x":-3.27,"y":-10.35,"curve":[0.023,-1.32,0.045,0,0.023,-4.16,0.045,0]},{"time":0.0667,"curve":[0.178,0,0.289,-31.46,0.178,0,0.289,-99.49]},{"time":0.4,"x":-31.46,"y":-99.49,"curve":[0.489,-31.46,0.579,-11.26,0.489,-99.49,0.579,-35.6]},{"time":0.6667,"x":-3.27,"y":-10.35}]},"arm_back":{"rotate":[{"value":3.91,"curve":[0.034,1.67,0.067,0]},{"time":0.1,"curve":[0.211,0,0.322,18.1]},{"time":0.4333,"value":18.1,"curve":[0.511,18.1,0.59,9.22]},{"time":0.6667,"value":3.91}]},"head":{"rotate":[{"value":0.72,"curve":[0.023,0.29,0.045,0]},{"time":0.0667,"curve":[0.178,0,0.289,6.88]},{"time":0.4,"value":6.88,"curve":[0.489,6.88,0.579,2.46]},{"time":0.6667,"value":0.72}]},"legs":{"rotate":[{"value":-2.44,"curve":[0.045,-1.12,0.089,0]},{"time":0.1333,"curve":[0.244,0,0.356,-6.92]},{"time":0.4667,"value":-6.92,"curve":[0.534,-6.92,0.601,-4.44]},{"time":0.6667,"value":-2.44}]},"legs1":{"rotate":[{"value":-2.44,"curve":[0.045,-1.12,0.089,0]},{"time":0.1333,"curve":[0.244,0,0.356,-6.92]},{"time":0.4667,"value":-6.92,"curve":[0.534,-6.92,0.601,-4.44]},{"time":0.6667,"value":-2.44}]}}},"stunned":{"slots":{"confuse":{"rgba":[{"color":"ffffffff"}]},"confuse2":{"rgba":[{"color":"ffffffff"}]},"confuse3":{"rgba":[{"color":"ffffffff"}]},"mouse_2":{"rgba":[{"color":"ffffffff"}]},"mouse_defolt":{"rgba":[{"color":"ffffff00"}]},"star":{"rgba":[{"color":"ffffffff"}]},"star2":{"rgba":[{"color":"ffffffff"}]},"star3":{"rgba":[{"color":"ffffffff"}]},"star4":{"rgba":[{"color":"ffffffff"}]}},"bones":{"torso":{"translate":[{"curve":[0.111,0,0.222,0,0.111,0,0.222,-42.57]},{"time":0.3333,"y":-42.57,"curve":[0.444,0,0.556,0,0.444,-42.57,0.556,0]},{"time":0.6667}]},"wing_front":{"shear":[{"curve":[0.037,0,0.063,-34.87,0.037,0,0.063,14.73]},{"time":0.1,"x":-34.87,"y":14.73,"curve":[0.137,-34.87,0.198,0,0.137,14.73,0.198,0]},{"time":0.2333,"curve":[0.27,0,0.296,-34.87,0.27,0,0.296,14.73]},{"time":0.3333,"x":-34.87,"y":14.73,"curve":[0.37,-34.87,0.398,0,0.37,14.73,0.398,0]},{"time":0.4333,"curve":[0.47,0,0.496,-34.87,0.47,0,0.496,14.73]},{"time":0.5333,"x":-34.87,"y":14.73,"curve":[0.57,-34.87,0.63,0,0.57,14.73,0.63,0]},{"time":0.6667}]},"wing_back":{"shear":[{"curve":[0.037,0,0.063,48.25,0.037,0,0.063,0]},{"time":0.1,"x":48.25,"curve":[0.137,48.25,0.198,0,0.137,0,0.198,0]},{"time":0.2333,"curve":[0.27,0,0.296,48.25,0.27,0,0.296,0]},{"time":0.3333,"x":48.25,"curve":[0.37,48.25,0.398,0,0.37,0,0.398,0]},{"time":0.4333,"curve":[0.47,0,0.496,48.25,0.47,0,0.496,0]},{"time":0.5333,"x":48.25,"curve":[0.57,48.25,0.63,0,0.57,0,0.63,0]},{"time":0.6667}]},"target":{"translate":[{"x":-92.76,"y":-107.94,"curve":[0.023,-95.5,0.045,-97.42,0.023,-107.52,0.045,-107.22]},{"time":0.0667,"x":-97.42,"y":-107.22,"curve":[0.167,-97.42,0.267,-45.81,0.167,-107.22,0.267,-115.25]},{"time":0.3667,"x":-45.81,"y":-115.25,"curve":[0.467,-45.81,0.567,-80.27,0.467,-115.25,0.567,-109.89]},{"time":0.6667,"x":-92.76,"y":-107.94}]},"arm_back":{"rotate":[{"value":15.8,"curve":[0.023,15.15,0.045,14.7]},{"time":0.0667,"value":14.7,"curve":[0.167,14.7,0.267,26.87]},{"time":0.3667,"value":26.87,"curve":[0.467,26.87,0.567,18.74]},{"time":0.6667,"value":15.8}]},"head":{"rotate":[{"value":59.7,"curve":[0.111,59.7,0.222,69.18]},{"time":0.3333,"value":69.18,"curve":[0.444,69.18,0.556,59.7]},{"time":0.6667,"value":59.7}]},"legs":{"rotate":[{"value":-2.44,"curve":[0.045,-1.12,0.089,0]},{"time":0.1333,"curve":[0.244,0,0.356,-6.92]},{"time":0.4667,"value":-6.92,"curve":[0.534,-6.92,0.601,-4.44]},{"time":0.6667,"value":-2.44}]},"legs1":{"rotate":[{"value":-2.44,"curve":[0.045,-1.12,0.089,0]},{"time":0.1333,"curve":[0.244,0,0.356,-6.92]},{"time":0.4667,"value":-6.92,"curve":[0.534,-6.92,0.601,-4.44]},{"time":0.6667,"value":-2.44}]},"wand_head":{"rotate":[{"value":54.33}]},"arm_back2":{"rotate":[{"value":45.74}]},"confuse":{"rotate":[{"value":12.65,"curve":[0.111,12.65,0.222,-3.39]},{"time":0.3333,"value":-3.39,"curve":[0.444,-3.39,0.556,12.65]},{"time":0.6667,"value":12.65}],"translate":[{"x":-658.96,"y":-42.06,"curve":[0.056,-658.96,0.111,-632.15,0.056,-42.06,0.111,-35.31]},{"time":0.1667,"x":-632.15,"y":-33.46,"curve":[0.222,-632.15,0.278,-656.18,0.222,-31.6,0.278,-31.43]},{"time":0.3333,"x":-666.04,"y":-30.93,"curve":[0.389,-675.91,0.444,-691.33,0.389,-30.42,0.444,-30.42]},{"time":0.5,"x":-691.33,"y":-30.42,"curve":[0.556,-691.33,0.611,-658.96,0.556,-30.42,0.611,-42.06]},{"time":0.6667,"x":-658.96,"y":-42.06}]},"confuse2":{"rotate":[{"value":-12.63,"curve":[0.111,-12.63,0.222,13.29]},{"time":0.3333,"value":13.29,"curve":[0.444,13.29,0.556,-12.63]},{"time":0.6667,"value":-12.63}],"translate":[{"x":-659.15,"y":-138.02,"curve":[0.111,-659.15,0.222,-658.65,0.111,-138.02,0.222,-158.76]},{"time":0.3333,"x":-658.65,"y":-158.76,"curve":[0.444,-658.65,0.556,-659.15,0.444,-158.76,0.556,-138.02]},{"time":0.6667,"x":-659.15,"y":-138.02}]},"confuse3":{"rotate":[{"value":17.98,"curve":[0.111,17.98,0.222,-32.55]},{"time":0.3333,"value":-32.55,"curve":[0.444,-32.55,0.556,17.98]},{"time":0.6667,"value":17.98}],"translate":[{"x":-657.28,"y":-282.58,"curve":[0.056,-657.28,0.111,-691.05,0.056,-282.58,0.111,-251.44]},{"time":0.1667,"x":-691.05,"y":-251.44,"curve":[0.222,-691.05,0.278,-662.68,0.222,-251.44,0.278,-255.55]},{"time":0.3333,"x":-652.99,"y":-257.74,"curve":[0.389,-643.29,0.444,-632.88,0.389,-259.93,0.444,-260.46]},{"time":0.5,"x":-632.88,"y":-264.6,"curve":[0.556,-632.88,0.611,-657.28,0.556,-268.74,0.611,-282.58]},{"time":0.6667,"x":-657.28,"y":-282.58}]},"star":{"translate":[{"x":-900.4,"y":-67.44},{"time":0.1667,"x":-714.06,"y":-77.08},{"time":0.3333,"x":-726.91,"y":2.16},{"time":0.5,"x":-881.12,"y":6.45},{"time":0.6667,"x":-900.4,"y":-67.44}]},"star2":{"translate":[{"x":-881.12,"y":-82.37},{"time":0.1667,"x":-900.4,"y":-156.26},{"time":0.3333,"x":-714.06,"y":-165.9},{"time":0.5,"x":-726.91,"y":-86.65},{"time":0.6667,"x":-881.12,"y":-82.37}]},"star3":{"translate":[{"x":-726.91,"y":-181.2},{"time":0.1667,"x":-881.12,"y":-176.91},{"time":0.3333,"x":-900.4,"y":-250.81},{"time":0.5,"x":-714.06,"y":-260.44},{"time":0.6667,"x":-726.91,"y":-181.2}]},"star4":{"translate":[{"x":-714.06,"y":-356.42},{"time":0.1667,"x":-726.91,"y":-277.18},{"time":0.3333,"x":-881.12,"y":-272.89},{"time":0.5,"x":-900.4,"y":-346.79},{"time":0.6667,"x":-714.06,"y":-356.42}]}}},"walk":{"bones":{"torso":{"translate":[{"curve":[0.111,0,0.222,0,0.111,0,0.222,-42.57]},{"time":0.3333,"y":-42.57,"curve":[0.444,0,0.556,0,0.444,-42.57,0.556,0]},{"time":0.6667}]},"wing_front":{"shear":[{"curve":[0.037,0,0.063,-34.87,0.037,0,0.063,14.73]},{"time":0.1,"x":-34.87,"y":14.73,"curve":[0.137,-34.87,0.198,0,0.137,14.73,0.198,0]},{"time":0.2333,"curve":[0.27,0,0.296,-34.87,0.27,0,0.296,14.73]},{"time":0.3333,"x":-34.87,"y":14.73,"curve":[0.37,-34.87,0.398,0,0.37,14.73,0.398,0]},{"time":0.4333,"curve":[0.47,0,0.496,-34.87,0.47,0,0.496,14.73]},{"time":0.5333,"x":-34.87,"y":14.73,"curve":[0.57,-34.87,0.63,0,0.57,14.73,0.63,0]},{"time":0.6667}]},"wing_back":{"shear":[{"curve":[0.037,0,0.063,48.25,0.037,0,0.063,0]},{"time":0.1,"x":48.25,"curve":[0.137,48.25,0.198,0,0.137,0,0.198,0]},{"time":0.2333,"curve":[0.27,0,0.296,48.25,0.27,0,0.296,0]},{"time":0.3333,"x":48.25,"curve":[0.37,48.25,0.398,0,0.37,0,0.398,0]},{"time":0.4333,"curve":[0.47,0,0.496,48.25,0.47,0,0.496,0]},{"time":0.5333,"x":48.25,"curve":[0.57,48.25,0.63,0,0.57,0,0.63,0]},{"time":0.6667}]},"target":{"translate":[{"x":-3.27,"y":-10.35,"curve":[0.023,-1.32,0.045,0,0.023,-4.16,0.045,0]},{"time":0.0667,"curve":[0.178,0,0.289,-31.46,0.178,0,0.289,-99.49]},{"time":0.4,"x":-31.46,"y":-99.49,"curve":[0.489,-31.46,0.579,-11.26,0.489,-99.49,0.579,-35.6]},{"time":0.6667,"x":-3.27,"y":-10.35}]},"arm_back":{"rotate":[{"value":3.91,"curve":[0.034,1.67,0.067,0]},{"time":0.1,"curve":[0.211,0,0.322,18.1]},{"time":0.4333,"value":18.1,"curve":[0.511,18.1,0.59,9.22]},{"time":0.6667,"value":3.91}]},"head":{"rotate":[{"value":0.72,"curve":[0.023,0.29,0.045,0]},{"time":0.0667,"curve":[0.178,0,0.289,6.88]},{"time":0.4,"value":6.88,"curve":[0.489,6.88,0.579,2.46]},{"time":0.6667,"value":0.72}]},"legs":{"rotate":[{"value":-2.44,"curve":[0.045,-1.12,0.089,0]},{"time":0.1333,"curve":[0.244,0,0.356,-6.92]},{"time":0.4667,"value":-6.92,"curve":[0.534,-6.92,0.601,-4.44]},{"time":0.6667,"value":-2.44}]},"legs1":{"rotate":[{"value":-2.44,"curve":[0.045,-1.12,0.089,0]},{"time":0.1333,"curve":[0.244,0,0.356,-6.92]},{"time":0.4667,"value":-6.92,"curve":[0.534,-6.92,0.601,-4.44]},{"time":0.6667,"value":-2.44}]}}}}}